sdreaper/__init__.py
sdreaper/app.py
sdreaper/main.py
sdreaper/reaper.py
sdreaper-1.0.1.dist-info/DESCRIPTION.rst
sdreaper-1.0.1.dist-info/METADATA
sdreaper-1.0.1.dist-info/RECORD
sdreaper-1.0.1.dist-info/WHEEL
sdreaper-1.0.1.dist-info/entry_points.txt
sdreaper-1.0.1.dist-info/metadata.json
sdreaper-1.0.1.dist-info/top_level.txt
