Metadata-Version: 2.0
Name: sdreaper
Version: 1.0.1
Summary: CLI and curses UI for talking to Arduino Reaper library
Home-page: https://github.com/humulabs/reaper/blob/master/README.md
Author: Michael Keirnan
Author-email: michael@keirnan.com
License: MIT
Keywords: arduino iot sd serial
Platform: any
Classifier: Development Status :: 4 - Beta
Classifier: Intended Audience :: Developers
Classifier: Intended Audience :: Science/Research
Classifier: Environment :: Console
Classifier: License :: OSI Approved :: MIT License
Classifier: Natural Language :: English
Classifier: Topic :: Home Automation
Classifier: Topic :: Internet
Classifier: Topic :: Software Development :: Libraries :: Python Modules
Classifier: Topic :: Scientific/Engineering
Classifier: Programming Language :: Python
Classifier: Programming Language :: Python :: 2
Classifier: Programming Language :: Python :: 2.7
Classifier: Programming Language :: Python :: 3
Classifier: Programming Language :: Python :: 3.4
Classifier: Programming Language :: Python :: 3.5
Requires-Dist: docopt
Requires-Dist: pyserial
Requires-Dist: urwid-timed-progress
